stopweb/__init__.py
stopweb/cli.py
stopweb/config.py
stopweb/duration.py
stopweb/hosts.py
stopweb/notify.py
stopweb-0.1.4.dist-info/METADATA
stopweb-0.1.4.dist-info/WHEEL
stopweb-0.1.4.dist-info/entry_points.txt
stopweb-0.1.4.dist-info/licenses/LICENSE
stopweb-0.1.4.dist-info/RECORD
