Metadata-Version: 2.4
Name: stopweb
Version: 0.1.4
Summary: A CLI tool to temporarily block websites by modifying the hosts file
License: MIT
License-File: LICENSE
Keywords: website,blocking,productivity,focus,hosts
Author: StopWeb
Author-email: stopweb@example.com
Requires-Python: >=3.8.1,<4.0.0
Classifier: Development Status :: 4 - Beta
Classifier: Intended Audience :: End Users/Desktop
Classifier: License :: OSI Approved :: MIT License
Classifier: Operating System :: OS Independent
Classifier: Programming Language :: Python :: 3
Classifier: Programming Language :: Python :: 3.9
Classifier: Programming Language :: Python :: 3.10
Classifier: Programming Language :: Python :: 3.11
Classifier: Programming Language :: Python :: 3.12
Classifier: Programming Language :: Python :: 3.13
Classifier: Programming Language :: Python :: 3.14
Classifier: Programming Language :: Python :: 3.8
Classifier: Topic :: Internet :: WWW/HTTP
Classifier: Topic :: System :: Networking
Requires-Dist: click (>=8.1.0,<9.0.0)
Requires-Dist: python-dateutil (>=2.8.2,<3.0.0)
Requires-Dist: rich (>=13.0.0,<14.0.0)
Project-URL: Homepage, https://github.com/stopweb/stopweb
Project-URL: Repository, https://github.com/stopweb/stopweb
